django_books/__init__.py
django_books/admin.py
django_books/apps.py
django_books/django-books.qwc
django_books/models.py
django_books/tests.py
django_books/urls.py
django_books/views.py
django_books/migrations/__init__.py
django_books/objects/__init__.py
django_books/objects/objects.py
django_books-0.0.3.dist-info/LICENSE
django_books-0.0.3.dist-info/METADATA
django_books-0.0.3.dist-info/WHEEL
django_books-0.0.3.dist-info/top_level.txt
django_books-0.0.3.dist-info/RECORD
